adafruit_ds3502.py
adafruit_circuitpython_ds3502-1.1.25.dist-info/licenses/LICENSE
adafruit_circuitpython_ds3502-1.1.25.dist-info/METADATA
adafruit_circuitpython_ds3502-1.1.25.dist-info/WHEEL
adafruit_circuitpython_ds3502-1.1.25.dist-info/top_level.txt
adafruit_circuitpython_ds3502-1.1.25.dist-info/RECORD
